xfold/alphafold3.py
xfold/feat_batch.py
xfold/features.py
xfold/geometry.py
xfold/params.py
xfold/protein_data_processing.py
xfold/scoring.py
xfold/version.py
xfold-0.0.1.dist-info/LICENSE
xfold-0.0.1.dist-info/METADATA
xfold-0.0.1.dist-info/WHEEL
xfold-0.0.1.dist-info/top_level.txt
xfold-0.0.1.dist-info/RECORD
