Metadata-Version: 2.1
Name: xfold
Version: 0.0.1
Summary: fold for everyone.
Author-email: Shenggan Cheng <shenggan.c@u.nus.edu>
License-File: LICENSE
Requires-Dist: torch
Requires-Dist: einops
